rupantaran/__init__.py
rupantaran/land/__init__.py
rupantaran/land/constants.py
rupantaran/land/cross_system.py
rupantaran/land/hilly.py
rupantaran/land/mixed_units.py
rupantaran/land/terai.py
rupantaran/tests/__init__.py
rupantaran/tests/land/__init__.py
rupantaran/tests/land/test_constants.py
rupantaran/tests/land/test_cross_system.py
rupantaran/tests/land/test_hilly.py
rupantaran/tests/land/test_mixed_units.py
rupantaran/tests/land/test_terai.py
rupantaran-0.2.0.dist-info/LICENSE
rupantaran-0.2.0.dist-info/METADATA
rupantaran-0.2.0.dist-info/WHEEL
rupantaran-0.2.0.dist-info/top_level.txt
rupantaran-0.2.0.dist-info/RECORD
